[
  {
    "year": 2012,
    "a": 5.709,
    "b": 67.013
  },
  {
    "year": 2013,
    "a": 5.288,
    "b": 87.189
  },
  {
    "year": 2014,
    "a": 4.899,
    "b": 69.511
  },
  {
    "year": 2015,
    "a": 4.095,
    "b": 80.422
  },
  {
    "year": 2016,
    "a": 4.645,
    "b": 70.716
  },
  {
    "year": 2017,
    "a": 10.208,
    "b": 64.448
  },
  {
    "year": 2018,
    "a": 9.292,
    "b": 55.044
  },
  {
    "year": 2019,
    "a": 3.886,
    "b": 78.001
  },
  {
    "year": 2020,
    "a": 6.989,
    "b": 84.391
  },
  {
    "year": 2021,
    "a": 5.192,
    "b": 61.388
  }
]
